skyengdict/__init__.py
skyengdict/dictionary.py
skyengdict/exc/__init__.py
skyengdict/exc/exceptions.py
skyengdict/types/__init__.py
skyengdict/types/types.py
skyengdict-1.0.12.dist-info/licenses/LICENSE
skyengdict-1.0.12.dist-info/METADATA
skyengdict-1.0.12.dist-info/WHEEL
skyengdict-1.0.12.dist-info/top_level.txt
skyengdict-1.0.12.dist-info/RECORD
