Metadata-Version: 2.4
Name: SkyengDict
Version: 1.0.12
Summary: Package for translation of Russian-English words
Author-email: ivan kornayhov <kiadu@bk.ru>
Project-URL: Homepage, https://github.com/ivakorn/skyengdict
Project-URL: Repository, https://github.com/ivakorn/skyengdict.git
Keywords: skyeng,translator,api,dictionary,vocolabry,lexicon,skyengdict
Classifier: Programming Language :: Python :: 3
Classifier: License :: OSI Approved :: MIT License
Classifier: Operating System :: OS Independent
Requires-Python: >=3.10
License-File: LICENSE
Requires-Dist: aiohttp
Requires-Dist: python-dateutil
Dynamic: license-file
